boutdata/__init__.py
boutdata/_version.py
boutdata/collect.py
boutdata/data.py
boutdata/griddata.py
boutdata/mms.py
boutdata/pol_slice.py
boutdata/processor_rearrange.py
boutdata/restart.py
boutdata/shiftz.py
boutdata/squashoutput.py
boutdata/scripts/__init__.py
boutdata/scripts/bout_squashoutput.py
boutdata/tests/__init__.py
boutdata/tests/make_test_data.py
boutdata/tests/test_boutoptions.py
boutdata/tests/test_collect.py
boutdata/tests/test_import.py
boutdata/tests/test_restart.py
boutdata-0.3.0.dist-info/licenses/LICENSE
boutupgrader/__init__.py
boutupgrader/bout_3to4.py
boutupgrader/bout_v5_factory_upgrader.py
boutupgrader/bout_v5_format_upgrader.py
boutupgrader/bout_v5_header_upgrader.py
boutupgrader/bout_v5_input_file_upgrader.py
boutupgrader/bout_v5_macro_upgrader.py
boutupgrader/bout_v5_physics_model_upgrader.py
boutupgrader/bout_v5_xzinterpolation_upgrader.py
boutupgrader/bout_v6_coordinates_upgrader.py
boutupgrader/bout_v6_input_file_upgrader.py
boutupgrader/common.py
boututils/View3D.py
boututils/__init__.py
boututils/anim.py
boututils/boutarray.py
boututils/boutgrid.py
boututils/boutwarnings.py
boututils/bunch.py
boututils/calculus.py
boututils/check_scaling.py
boututils/datafile.py
boututils/fft_integrate.py
boututils/int_func.py
boututils/linear_regression.py
boututils/mode_structure.py
boututils/moment_xyzt.py
boututils/plotdata.py
boututils/run_wrapper.py
boututils/showdata.py
boututils/spectrogram.py
boututils/surface_average.py
boututils/volume_integral.py
boututils/tests/__init__.py
boututils/tests/test_import.py
boutdata-0.3.0.dist-info/METADATA
boutdata-0.3.0.dist-info/WHEEL
boutdata-0.3.0.dist-info/entry_points.txt
boutdata-0.3.0.dist-info/top_level.txt
boutdata-0.3.0.dist-info/RECORD
