Metadata-Version: 2.4
Name: boutdata
Version: 0.3.0
Summary: Python package for collecting BOUT++ data
Author: BOUT++ team
Author-email: Ben Dudson <benjamin.dudson@york.ac.uk>
License: GNU Lesser General Public License v3 or later (LGPLv3+)
Project-URL: project, https://github.com/boutproject/boutdata
Keywords: bout++,bout,plasma,physics,data-extraction,data-analysis,data-visualization
Classifier: Programming Language :: Python
Classifier: Intended Audience :: Science/Research
Classifier: License :: OSI Approved :: GNU Lesser General Public License v3 or later (LGPLv3+)
Classifier: Operating System :: OS Independent
Classifier: Programming Language :: Python
Classifier: Topic :: Software Development :: Libraries :: Python Modules
Requires-Python: >=3.9
License-File: LICENSE
Requires-Dist: sympy>=1.5.1
Requires-Dist: numpy>=1.22.0
Requires-Dist: matplotlib>=3.2.1
Requires-Dist: natsort>=8.1.0
Requires-Dist: scipy>=1.4.1
Requires-Dist: netCDF4
Provides-Extra: tests
Requires-Dist: pytest; extra == "tests"
Provides-Extra: docs
Requires-Dist: sphinx<5,>=3.4; extra == "docs"
Provides-Extra: lint
Requires-Dist: ruff; extra == "lint"
Dynamic: license-file
